README.md
setup.cfg
setup.py
bin/easy_tst
easy_tst/__init__.py
easy_tst/__version__.py
easy_tst/easy_helper.py
easy_tst/easy_organizer.py
easy_tst/easy_watcher.py
easy_tst/tst_wrapper.py
easy_tst.egg-info/PKG-INFO
easy_tst.egg-info/SOURCES.txt
easy_tst.egg-info/dependency_links.txt
easy_tst.egg-info/requires.txt
easy_tst.egg-info/top_level.txt