Metadata-Version: 1.1
Name: easy-tst
Version: 2.0.0
Summary: tst automatically
Home-page: https://github.com/brobsc/easy_tst
Author: Bruno Siqueira, Joao Espindula
Author-email: bruno.siqueira@ccc.ufcg.edu.br
License: UNKNOWN
Download-URL: https://github.com/brobsc/easy_tst/archive/2.0.0.tar.gz
Platform: UNKNOWN
